AUTHORS
LICENSE
MANIFEST.in
README.rst
setup.py
postman/__init__.py
postman/__main__.py
postman.egg-info/PKG-INFO
postman.egg-info/SOURCES.txt
postman.egg-info/dependency_links.txt
postman.egg-info/entry_points.txt
postman.egg-info/not-zip-safe
postman.egg-info/requires.txt
postman.egg-info/top_level.txt