Metadata-Version: 1.0
Name: postman
Version: 0.5.2
Summary: Command line for Amazon SES
Home-page: UNKNOWN
Author: Patrick Altman
Author-email: paltman@gmail.com
License: UNKNOWN
Platform: UNKNOWN
